pineboolib/__init__.py
pineboolib/py.typed
pineboolib/application/__init__.py
pineboolib/application/connections.py
pineboolib/application/file.py
pineboolib/application/load_script.py
pineboolib/application/module.py
pineboolib/application/moduleactions.py
pineboolib/application/modules_tree.py
pineboolib/application/pnapplication.py
pineboolib/application/pncore.py
pineboolib/application/process.py
pineboolib/application/projectmodule.py
pineboolib/application/proxy.py
pineboolib/application/qsadictmodules.py
pineboolib/application/safeqsa.py
pineboolib/application/types.py
pineboolib/application/xmlaction.py
pineboolib/application/acls/__init__.py
pineboolib/application/acls/pnaccesscontrol.py
pineboolib/application/acls/pnaccesscontrolfactory.py
pineboolib/application/acls/pnaccesscontrollists.py
pineboolib/application/acls/pnboolflagstate.py
pineboolib/application/acls/tests/__init__.py
pineboolib/application/acls/tests/test_acls.py
pineboolib/application/acls/tests/test_pnaccesscontrol.py
pineboolib/application/database/__init__.py
pineboolib/application/database/pnbuffer.py
pineboolib/application/database/pnconnection.py
pineboolib/application/database/pnconnectionmanager.py
pineboolib/application/database/pncursortablemodel.py
pineboolib/application/database/pngroupbyquery.py
pineboolib/application/database/pnparameterquery.py
pineboolib/application/database/pnsignals.py
pineboolib/application/database/pnsqlcursor.py
pineboolib/application/database/pnsqldriversmanager.py
pineboolib/application/database/pnsqlquery.py
pineboolib/application/database/utils.py
pineboolib/application/database/orm/__init__.py
pineboolib/application/database/orm/alembic_tools.py
pineboolib/application/database/orm/basemodel.py
pineboolib/application/database/orm/dummy_cursor.py
pineboolib/application/database/orm/dummy_signal.py
pineboolib/application/database/orm/utils.py
pineboolib/application/database/orm/tests/__init__.py
pineboo-1.0.5.dist-info/LICENSE.mit
pineboo-1.0.5.dist-info/METADATA
pineboo-1.0.5.dist-info/WHEEL
pineboo-1.0.5.dist-info/entry_points.txt
pineboo-1.0.5.dist-info/top_level.txt
pineboo-1.0.5.dist-info/RECORD
