Metadata-Version: 2.1
Name: pineboo
Version: 1.0.5
Summary: ERP replacement for Eneboo written in Python
Home-page: https://github.com/deavid/pineboo
Author: David Martínez Martí, José A. Fernández Fernández
Author-email: deavidsedice@gmail.com, aullasistemas@gmail.com
Keywords: erp pineboo eneboo accounting sales warehouse
Classifier: Development Status :: 5 - Production/Stable
Classifier: License :: OSI Approved :: MIT License
Classifier: Programming Language :: Python :: 3 :: Only
Classifier: Programming Language :: Python :: 3
Classifier: Programming Language :: Python :: 3.7
Classifier: Programming Language :: Python :: 3.8
Classifier: Programming Language :: Python :: 3.9
Classifier: Programming Language :: Python :: 3.10
Classifier: Programming Language :: Python :: 3.11
Classifier: Environment :: X11 Applications :: Qt
Classifier: Topic :: Office/Business :: Financial :: Accounting
Classifier: Typing :: Typed
Classifier: Intended Audience :: End Users/Desktop
Classifier: Intended Audience :: Developers
Classifier: Natural Language :: English
Classifier: Natural Language :: Spanish
Classifier: Operating System :: OS Independent
Requires-Python: >=3.7
License-File: LICENSE.mit
Requires-Dist: alembic (>=1.7.7)
Requires-Dist: black (==22.6.0)
Requires-Dist: clipboard (==0.0.4)
Requires-Dist: coloredlogs (==14.0)
Requires-Dist: cryptography (==36.0.1)
Requires-Dist: fernet (==1.0.1)
Requires-Dist: fpdf2 (==2.4.2)
Requires-Dist: flake8 (==3.9.0)
Requires-Dist: flup (==1.0.3)
Requires-Dist: fonttools (>=4.27.1)
Requires-Dist: keyrings.alt (>=3.4.0)
Requires-Dist: lxml (==4.9.1)
Requires-Dist: marshmallow (>=3.19.0)
Requires-Dist: ninja (==1.10.0.post1)
Requires-Dist: odfpy
Requires-Dist: pdf2image (==1.14.0)
Requires-Dist: ply (==3.11)
Requires-Dist: poppler-utils
Requires-Dist: psycopg2
Requires-Dist: pyroma (==2.6)
Requires-Dist: pyfiglet
Requires-Dist: pyHanko[opentype] (==0.13.2)
Requires-Dist: pyOpenSSL (==20.0.1)
Requires-Dist: pympler
Requires-Dist: python-barcode
Requires-Dist: python-daemon
Requires-Dist: qrcode[pil]
Requires-Dist: sqlalchemy (==2.0.3)
Requires-Dist: sqlparse (==0.3.1)
Requires-Dist: twine (==3.1.1)
Requires-Dist: uharfbuzz (>=0.25.0)
Requires-Dist: watchdog (>=0.10.2)
Requires-Dist: xades (==0.2.1)
Requires-Dist: xmlsig (==0.1.7)
Requires-Dist: Pillow (==9.4.0)
Requires-Dist: PyYAML (==5.3.1)
Requires-Dist: PyQt6 (>=6.2.3)
Requires-Dist: PyQt6-Qt6 (>=6.2.3)
Requires-Dist: PyQt6-sip (>=13.2.1)
